thatgaypigeon/__init__.py
thatgaypigeon/thatgaypigeon.py
thatgaypigeon-0.0.0a0.dev0.dist-info/METADATA
thatgaypigeon-0.0.0a0.dev0.dist-info/WHEEL
thatgaypigeon-0.0.0a0.dev0.dist-info/licenses/LICENSE
thatgaypigeon-0.0.0a0.dev0.dist-info/RECORD
