Metadata-Version: 2.1
Name: thatgaypigeon
Version: 0.0.0a0.dev0
Summary: thatgaypigeon
Project-URL: Documentation, http://thatgaypigeon-py.rtfd.io/
Project-URL: Homepage, https://github.com/thatgaypigeon/thatgaypigeon-py
Project-URL: Issues / Bugs, https://github.com/thatgaypigeon/thatgaypigeon-py/issues
Project-URL: PyPI, https://pypi.org/project/thatgaypigeon/
Project-URL: Support Server, https://discord.gg/MyPTZBH4Q8
Author-email: thatgaypigeon <rapidpigeon43@gmail.com>
License: The MIT License (MIT)
License-File: LICENSE
Keywords: thatgaypigeon
Classifier: Development Status :: 1 - Planning
Classifier: Intended Audience :: Developers
Classifier: License :: OSI Approved
Classifier: License :: OSI Approved :: MIT License
Classifier: Natural Language :: English
Classifier: Operating System :: OS Independent
Classifier: Programming Language :: Python
Classifier: Programming Language :: Python :: 3.8
Classifier: Programming Language :: Python :: 3.9
Classifier: Programming Language :: Python :: 3.10
Classifier: Programming Language :: Python :: 3.11
Classifier: Topic :: Other/Nonlisted Topic
Classifier: Topic :: Software Development
Classifier: Topic :: Software Development :: Libraries
Classifier: Topic :: Software Development :: Libraries :: Python Modules
Classifier: Typing :: Typed
Requires-Python: >=3.8
